dwhtools/__init__.py
dwhtools/dataCleansing.py
dwhtools/dateTable.py
dwhtools/scdTools.py
dwhtools/testing.py
dwhtools-0.0.2.1009.dist-info/METADATA
dwhtools-0.0.2.1009.dist-info/WHEEL
dwhtools-0.0.2.1009.dist-info/top_level.txt
dwhtools-0.0.2.1009.dist-info/RECORD
