Metadata-Version: 2.1
Name: dwhtools
Version: 0.0.2.1009
Summary: Dies ist eine kurze Beschreibung
Home-page: UNKNOWN
Author: Bejamin Weber
Author-email: b.weber@oraylis.de
License: UNKNOWN
Platform: UNKNOWN
